{
    "id": "b1b12711-97fa-11ef-b1e1-49612c63f05a",
    "charts": [
        {
            "n": 2,
            "m": 2,
            "quad": {
                "p1": {
                    "x": 0.10635216666228797,
                    "y": 0.27272713853941455
                },
                "p2": {
                    "x": 0.5,
                    "y": 0.5
                },
                "p3": {
                    "x": 0.8936479882845042,
                    "y": 0.2727274069151314
                },
                "p4": {
                    "x": 0.5000001549467925,
                    "y": 0.04545454545454536
                }
            }
        },
        {
            "n": 2,
            "m": 2,
            "quad": {
                "p1": {
                    "x": 0.10635216666228836,
                    "y": 0.2727271385394142
                },
                "p2": {
                    "x": 0.10635201171549563,
                    "y": 0.7272725930848692
                },
                "p3": {
                    "x": 0.49999984505320805,
                    "y": 0.9545454545454546
                },
                "p4": {
                    "x": 0.49999999999999933,
                    "y": 0.5000000000000003
                }
            }
        },
        {
            "n": 2,
            "m": 2,
            "quad": {
                "p1": {
                    "x": 0.49999999999999933,
                    "y": 0.5000000000000003
                },
                "p2": {
                    "x": 0.4999998450532087,
                    "y": 0.9545454545454546
                },
                "p3": {
                    "x": 0.893647833337712,
                    "y": 0.7272728614605857
                },
                "p4": {
                    "x": 0.8936479882845039,
                    "y": 0.27272740691513186
                }
            }
        }
    ],
    "connections": [
        {
            "fromA": 0,
            "toA": 1,
            "rot": {
                "x": 2,
                "y": 0
            },
            "trans": {
                "x": 0,
                "y": -2
            }
        },
        {
            "fromA": 0,
            "toA": 2,
            "rot": {
                "x": 0,
                "y": 2
            },
            "trans": {
                "x": 0,
                "y": -4
            }
        },
        {
            "fromA": 1,
            "toA": 2,
            "rot": {
                "x": 0,
                "y": 2
            },
            "trans": {
                "x": -4,
                "y": 0
            }
        }
    ],
    "constraints": {
        "coincidents": [
            {
                "coords": [
                    {
                        "a": 1,
                        "hk": {
                            "x": -1,
                            "y": -1
                        }
                    },
                    {
                        "a": 0,
                        "hk": {
                            "x": -1,
                            "y": -1
                        }
                    }
                ]
            },
            {
                "coords": [
                    {
                        "a": 1,
                        "hk": {
                            "x": 3,
                            "y": 3
                        }
                    },
                    {
                        "a": 2,
                        "hk": {
                            "x": -1,
                            "y": 3
                        }
                    }
                ]
            },
            {
                "coords": [
                    {
                        "a": 2,
                        "hk": {
                            "x": 3,
                            "y": -1
                        }
                    },
                    {
                        "a": 0,
                        "hk": {
                            "x": 3,
                            "y": 3
                        }
                    }
                ]
            },
            {
                "coords": [
                    {
                        "a": 2,
                        "hk": {
                            "x": -1,
                            "y": -1
                        }
                    },
                    {
                        "a": 0,
                        "hk": {
                            "x": -1,
                            "y": 3
                        }
                    },
                    {
                        "a": 1,
                        "hk": {
                            "x": 3,
                            "y": -1
                        }
                    }
                ]
            }
        ],
        "equidistants": [
            {
                "sides": [
                    {
                        "c1": {
                            "a": 1,
                            "hk": {
                                "x": 3,
                                "y": 3
                            }
                        },
                        "c2": {
                            "a": 1,
                            "hk": {
                                "x": -1,
                                "y": 3
                            }
                        }
                    },
                    {
                        "c1": {
                            "a": 1,
                            "hk": {
                                "x": 3,
                                "y": 3
                            }
                        },
                        "c2": {
                            "a": 0,
                            "hk": {
                                "x": -1,
                                "y": 3
                            }
                        }
                    },
                    {
                        "c1": {
                            "a": 2,
                            "hk": {
                                "x": 3,
                                "y": 3
                            }
                        },
                        "c2": {
                            "a": 1,
                            "hk": {
                                "x": 3,
                                "y": 3
                            }
                        }
                    },
                    {
                        "c1": {
                            "a": 0,
                            "hk": {
                                "x": 3,
                                "y": 3
                            }
                        },
                        "c2": {
                            "a": 2,
                            "hk": {
                                "x": 3,
                                "y": 3
                            }
                        }
                    },
                    {
                        "c1": {
                            "a": 0,
                            "hk": {
                                "x": 3,
                                "y": -1
                            }
                        },
                        "c2": {
                            "a": 0,
                            "hk": {
                                "x": 3,
                                "y": 3
                            }
                        }
                    },
                    {
                        "c1": {
                            "a": 0,
                            "hk": {
                                "x": -1,
                                "y": -1
                            }
                        },
                        "c2": {
                            "a": 0,
                            "hk": {
                                "x": 3,
                                "y": -1
                            }
                        }
                    },
                    {
                        "c1": {
                            "a": 1,
                            "hk": {
                                "x": -1,
                                "y": 3
                            }
                        },
                        "c2": {
                            "a": 0,
                            "hk": {
                                "x": -1,
                                "y": -1
                            }
                        }
                    },
                    {
                        "c1": {
                            "a": 0,
                            "hk": {
                                "x": -1,
                                "y": 3
                            }
                        },
                        "c2": {
                            "a": 1,
                            "hk": {
                                "x": -1,
                                "y": 3
                            }
                        }
                    },
                    {
                        "c1": {
                            "a": 0,
                            "hk": {
                                "x": 3,
                                "y": -1
                            }
                        },
                        "c2": {
                            "a": 0,
                            "hk": {
                                "x": -1,
                                "y": 3
                            }
                        }
                    },
                    {
                        "c1": {
                            "a": 0,
                            "hk": {
                                "x": -1,
                                "y": 3
                            }
                        },
                        "c2": {
                            "a": 0,
                            "hk": {
                                "x": -1,
                                "y": -1
                            }
                        }
                    },
                    {
                        "c1": {
                            "a": 0,
                            "hk": {
                                "x": 3,
                                "y": 3
                            }
                        },
                        "c2": {
                            "a": 0,
                            "hk": {
                                "x": -1,
                                "y": 3
                            }
                        }
                    },
                    {
                        "c1": {
                            "a": 0,
                            "hk": {
                                "x": -1,
                                "y": 3
                            }
                        },
                        "c2": {
                            "a": 2,
                            "hk": {
                                "x": 3,
                                "y": 3
                            }
                        }
                    }
                ]
            }
        ]
    }
}